kilroy_module_huggingface/__init__.py
kilroy_module_huggingface/__main__.py
kilroy_module_huggingface/config.py
kilroy_module_huggingface/log.py
kilroy_module_huggingface/models/__init__.py
kilroy_module_huggingface/models/loader.py
kilroy_module_huggingface/models/models.py
kilroy_module_huggingface/models/tokenizer.py
kilroy_module_huggingface/module.py
kilroy_module_huggingface/resources/__init__.py
kilroy_module_huggingface/resources/config.yaml
kilroy_module_huggingface/utils.py
kilroy_module_huggingface-0.7.5.dist-info/entry_points.txt
kilroy_module_huggingface-0.7.5.dist-info/LICENSE
kilroy_module_huggingface-0.7.5.dist-info/WHEEL
kilroy_module_huggingface-0.7.5.dist-info/METADATA
kilroy_module_huggingface-0.7.5.dist-info/RECORD
